general_utils_j/__init__.py
general_utils_j/colors.py
general_utils_j/prints.py
general_utils_j/umaths.py
general_utils_j/clases_auxiliares/__init__.py
general_utils_j/clases_auxiliares/punto.py
general_utils_j/patrones/__init__.py
general_utils_j/patrones/singleton.py
general_utils_juan_palma_borda-0.2.2.dist-info/LICENSE
general_utils_juan_palma_borda-0.2.2.dist-info/LICENSE.txt
general_utils_juan_palma_borda-0.2.2.dist-info/METADATA
general_utils_juan_palma_borda-0.2.2.dist-info/WHEEL
general_utils_juan_palma_borda-0.2.2.dist-info/top_level.txt
general_utils_juan_palma_borda-0.2.2.dist-info/RECORD
