Metadata-Version: 2.1
Name: general-utils-juan-palma-borda
Version: 0.2.2
Summary: Group of general utils from different projects.
Home-page: https://github.com/muerterauda/general-utils
Author: Juan Palma Borda
Author-email: Juan Palma Borda <juanpalmaborda@hotmail.com>
Keywords: utils,colors,prints,math_operations
Classifier: Programming Language :: Python :: 3
Requires-Python: >=3.6
License-File: LICENSE
License-File: LICENSE.txt
